setup.py
scripts/whisperctl
whisperctl/__init__.py
whisperctl/whisperctl.py
whisperctl.egg-info/PKG-INFO
whisperctl.egg-info/SOURCES.txt
whisperctl.egg-info/dependency_links.txt
whisperctl.egg-info/requires.txt
whisperctl.egg-info/top_level.txt
whisperctl/indexer/__init__.py
whisperctl/indexer/indexer.py