Metadata-Version: 1.0
Name: whisperctl
Version: 0.2.0
Summary: A tool for managing Whisper databases used in Graphite.
Home-page: http://github.com/josephl/whisperctl
Author: Joseph Lee
Author-email: joseph@idealist.org
License: MIT
Keywords: whisper,graphite,carbon,statsd
Platform: UNKNOWN
